agentgatepay_sdk/__init__.py
agentgatepay_sdk/client.py
agentgatepay_sdk/config_loader.py
agentgatepay_sdk/exceptions.py
agentgatepay_sdk/http_client.py
agentgatepay_sdk/modules/__init__.py
agentgatepay_sdk/modules/analytics.py
agentgatepay_sdk/modules/audit.py
agentgatepay_sdk/modules/auth.py
agentgatepay_sdk/modules/mandates.py
agentgatepay_sdk/modules/mcp.py
agentgatepay_sdk/modules/payments.py
agentgatepay_sdk/modules/webhooks.py
agentgatepay_sdk-1.1.6.dist-info/licenses/LICENSE
agentgatepay_sdk-1.1.6.dist-info/METADATA
agentgatepay_sdk-1.1.6.dist-info/WHEEL
agentgatepay_sdk-1.1.6.dist-info/top_level.txt
agentgatepay_sdk-1.1.6.dist-info/RECORD
