Metadata-Version: 2.4
Name: agentgatepay-sdk
Version: 1.1.6
Summary: Official Python SDK for AgentGatePay - Secure Payment Gateway for AI agents
Home-page: https://github.com/AgentGatePay/agentgatepay-sdks
Author: AgentGatePay
Author-email: AgentGatePay <support@agentgatepay.io>
License: MIT
Project-URL: Homepage, https://github.com/agentgatepay/agentgatepay-python-sdk
Project-URL: Documentation, https://docs.agentgatepay.io
Project-URL: Repository, https://github.com/agentgatepay/agentgatepay-python-sdk
Project-URL: Issues, https://github.com/agentgatepay/agentgatepay-python-sdk/issues
Keywords: agentgatepay,payments,ai-agents,crypto,web3,ap2,x402
Classifier: Programming Language :: Python :: 3
Classifier: License :: OSI Approved :: MIT License
Classifier: Operating System :: OS Independent
Requires-Python: >=3.8
License-File: LICENSE
Requires-Dist: requests>=2.31.0
Provides-Extra: web3
Requires-Dist: web3>=6.0.0; extra == "web3"
Provides-Extra: dev
Requires-Dist: pytest>=7.0.0; extra == "dev"
Requires-Dist: black>=23.0.0; extra == "dev"
Requires-Dist: mypy>=1.0.0; extra == "dev"
Dynamic: author
Dynamic: home-page
Dynamic: license-file
Dynamic: requires-python
